helloworld.py
helloworld_sida-0.0.1.dist-info/LICENSE
helloworld_sida-0.0.1.dist-info/METADATA
helloworld_sida-0.0.1.dist-info/WHEEL
helloworld_sida-0.0.1.dist-info/top_level.txt
helloworld_sida-0.0.1.dist-info/RECORD
